dir_print/__init__.py
dir_print/main.py
DirPrint-0.2.9.dist-info/LICENSE
DirPrint-0.2.9.dist-info/METADATA
DirPrint-0.2.9.dist-info/WHEEL
DirPrint-0.2.9.dist-info/entry_points.txt
DirPrint-0.2.9.dist-info/top_level.txt
DirPrint-0.2.9.dist-info/RECORD
