Metadata-Version: 2.1
Name: DirPrint
Version: 0.2.9
Summary: DirPrint: Print your directory structure and file contents with ease.
Home-page: https://github.com/zebangeth/DirPrint
Author: zebang.eth
Author-email: zebang_li@berkeley.edu
Classifier: Programming Language :: Python :: 3
Classifier: License :: OSI Approved :: MIT License
Classifier: Operating System :: OS Independent
Requires-Python: >=3.6
License-File: LICENSE
